jupyterlab_autoscrollcelloutput/__init__.py
jupyterlab_autoscrollcelloutput/_version.py
jupyterlab_autoscrollcelloutput/labextension/build_log.json
jupyterlab_autoscrollcelloutput/labextension/package.json
jupyterlab_autoscrollcelloutput/labextension/static/66d3c8490a113cebcd31e5dc7188dd547aefee0c554f6e69eaa98cdc763aaa8e.png
jupyterlab_autoscrollcelloutput/labextension/static/lib_index_js.01d5ee18a030ec05b242.js
jupyterlab_autoscrollcelloutput/labextension/static/lib_index_js.01d5ee18a030ec05b242.js.map
jupyterlab_autoscrollcelloutput/labextension/static/lib_index_js.1672297a242c695a1992.js
jupyterlab_autoscrollcelloutput/labextension/static/lib_index_js.1672297a242c695a1992.js.map
jupyterlab_autoscrollcelloutput/labextension/static/lib_index_js.18b7bc690ea4c5a60a45.js
jupyterlab_autoscrollcelloutput/labextension/static/lib_index_js.18b7bc690ea4c5a60a45.js.map
jupyterlab_autoscrollcelloutput/labextension/static/lib_index_js.1945d82adaf2735d8321.js
jupyterlab_autoscrollcelloutput/labextension/static/lib_index_js.1945d82adaf2735d8321.js.map
jupyterlab_autoscrollcelloutput/labextension/static/lib_index_js.1be4e3b6247440582360.js
jupyterlab_autoscrollcelloutput/labextension/static/lib_index_js.1be4e3b6247440582360.js.map
jupyterlab_autoscrollcelloutput/labextension/static/lib_index_js.43de1681aac997cc5104.js
jupyterlab_autoscrollcelloutput/labextension/static/lib_index_js.43de1681aac997cc5104.js.map
jupyterlab_autoscrollcelloutput/labextension/static/lib_index_js.49ca1c4ce17641a45c88.js
jupyterlab_autoscrollcelloutput/labextension/static/lib_index_js.49ca1c4ce17641a45c88.js.map
jupyterlab_autoscrollcelloutput/labextension/static/lib_index_js.5c0ce75d28ac2c8edfe1.js
jupyterlab_autoscrollcelloutput/labextension/static/lib_index_js.5c0ce75d28ac2c8edfe1.js.map
jupyterlab_autoscrollcelloutput/labextension/static/lib_index_js.7459620545dc8e68deaa.js
jupyterlab_autoscrollcelloutput/labextension/static/lib_index_js.7459620545dc8e68deaa.js.map
jupyterlab_autoscrollcelloutput-0.1.2.dist-info/LICENSE
jupyterlab_autoscrollcelloutput-0.1.2.dist-info/METADATA
jupyterlab_autoscrollcelloutput-0.1.2.dist-info/WHEEL
jupyterlab_autoscrollcelloutput-0.1.2.dist-info/top_level.txt
jupyterlab_autoscrollcelloutput-0.1.2.dist-info/RECORD
